pero_ocr/__init__.py
pero_ocr/char_confidences.py
pero_ocr/error_summary.py
pero_ocr/line_images_io.py
pero_ocr/sequence_alignment.py
pero_ocr/transcription_io.py
pero_ocr/utils.py
pero_ocr/core/__init__.py
pero_ocr/core/arabic_helper.py
pero_ocr/core/confidence_estimation.py
pero_ocr/core/crop_engine.py
pero_ocr/core/force_alignment.py
pero_ocr/core/layout.py
pero_ocr/decoding/__init__.py
pero_ocr/decoding/bag_of_hypotheses.py
pero_ocr/decoding/confusion_networks.py
pero_ocr/decoding/decoders.py
pero_ocr/decoding/decoding_itf.py
pero_ocr/decoding/lm_wrapper.py
pero_ocr/decoding/multisort.py
pero_ocr/document_ocr/__init__.py
pero_ocr/document_ocr/page_parser.py
pero_ocr/document_ocr/pdf_production.py
pero_ocr/layout_engines/__init__.py
pero_ocr/layout_engines/baseline_refiner.py
pero_ocr/layout_engines/cnn_layout_engine.py
pero_ocr/layout_engines/layout_helpers.py
pero_ocr/layout_engines/line_in_region_detector.py
pero_ocr/layout_engines/line_postprocessing_engine.py
pero_ocr/layout_engines/naive_sorter.py
pero_ocr/layout_engines/simple_baseline_engine.py
pero_ocr/layout_engines/simple_region_engine.py
pero_ocr/layout_engines/smart_sorter.py
pero_ocr/layout_engines/torch_parsenet.py
pero_ocr/ocr_engine/__init__.py
pero_ocr/ocr_engine/line_ocr_engine.py
pero_ocr/ocr_engine/postprocess.py
pero_ocr/ocr_engine/pytorch_ocr_engine.py
pero_ocr/ocr_engine/softmax.py
pero_ocr/ocr_engine/transformer.py
pero_ocr/ocr_engine/transformer_ocr_engine.py
pero_ocr/user_scripts/compare_page_xml_texts.py
pero_ocr/user_scripts/merge_ocr_results.py
pero_ocr/user_scripts/parse_folder.py
pero_ocr/user_scripts/produce_2layer_pdf.py
pero_ocr/user_scripts/select_embed_id.py
pero_ocr-0.7.0.dist-info/LICENSE
pero_ocr-0.7.0.dist-info/METADATA
pero_ocr-0.7.0.dist-info/WHEEL
pero_ocr-0.7.0.dist-info/entry_points.txt
pero_ocr-0.7.0.dist-info/top_level.txt
pero_ocr-0.7.0.dist-info/RECORD
