Metadata-Version: 2.1
Name: pero-ocr
Version: 0.7.0
Summary: Toolkit for advanced OCR of poor quality documents
Author-email: Michal Hradiš <hradis@fit.vutbr.cz>
Maintainer-email: Karel Beneš <ibenes@fit.vutbr.cz>
License: BSD 3-Clause License
Project-URL: homepage, https://pero.fit.vutbr.cz/
Project-URL: repository, https://github.com/DCGM/pero-ocr
Keywords: OCR,Layout analysis,handwriting recognition
Classifier: Programming Language :: Python :: 3
Classifier: License :: OSI Approved :: BSD License
Classifier: Operating System :: OS Independent
Requires-Python: >=3.9
License-File: LICENSE
Requires-Dist: numpy
Requires-Dist: opencv-python
Requires-Dist: lxml
Requires-Dist: lmdb
Requires-Dist: levenshtein
Requires-Dist: scipy
Requires-Dist: numba
Requires-Dist: torch >=2.0.1
Requires-Dist: torchvision >=0.15.2
Requires-Dist: brnolm >=0.3.0
Requires-Dist: scikit-learn
Requires-Dist: scikit-image
Requires-Dist: shapely
Requires-Dist: safe-gpu >=1.5.1
Requires-Dist: pyamg
Requires-Dist: imgaug
Requires-Dist: arabic-reshaper
